{
  "release_year": 1969,
  "release_month": 6,
  "issues": [
    {
      "key": -1453,
      "index": 778,
      "title": 3,
      "issue": 117,
      "issuetype": 1,
      "grade": 6.5,
      "weight": 1,
      "filename": "CAP_117"
    },
    {
      "key": -1452,
      "index": 779,
      "title": 9,
      "issue": 17,
      "issuetype": 1,
      "grade": 6.5,
      "weight": 1,
      "filename": "IRON_17"
    },
    {
      "key": -1451,
      "index": 780,
      "title": 6,
      "issue": 14,
      "issuetype": 1,
      "grade": 2.5,
      "weight": 1,
      "filename": "FURY_14"
    },
    {
      "key": -1450,
      "index": 781,
      "title": 19,
      "issue": 167,
      "issuetype": 1,
      "grade": 8,
      "weight": 1,
      "filename": "THOR_167"
    },
    {
      "key": -1449,
      "index": 782,
      "title": 2,
      "issue": 67,
      "issuetype": 1,
      "grade": 7,
      "weight": 1,
      "filename": "AVEN_67"
    },
    {
      "key": -1448,
      "index": 783,
      "title": 12,
      "issue": 16,
      "issuetype": 1,
      "grade": 7.5,
      "weight": 1,
      "filename": "MAR-VELL_16"
    },
    {
      "key": -1447,
      "index": 784,
      "title": 16,
      "issue": 182,
      "issuetype": 1,
      "grade": 7,
      "weight": 1,
      "filename": "STRANGE_182"
    },
    {
      "key": -1446,
      "index": 785,
      "title": 7,
      "issue": 119,
      "issuetype": 1,
      "grade": 4,
      "weight": 1,
      "filename": "HULK_119"
    },
    {
      "key": -1445,
      "index": 786,
      "title": 17,
      "issue": 17,
      "issuetype": 1,
      "grade": 3,
      "weight": 1,
      "filename": "SUB_17"
    },
    {
      "key": -1444,
      "index": 787,
      "title": 1,
      "issue": 76,
      "issuetype": 1,
      "grade": 6.5,
      "weight": 1,
      "filename": "ASM_76"
    },
    {
      "key": -1443,
      "index": 788,
      "title": 4,
      "issue": 55,
      "issuetype": 1,
      "grade": 2,
      "weight": 1,
      "filename": "DD_55"
    },
    {
      "key": -1442,
      "index": 789,
      "title": 5,
      "issue": 90,
      "issuetype": 1,
      "grade": 5,
      "weight": 1,
      "filename": "FF_90"
    },
    {
      "key": -1441,
      "index": 790,
      "title": 18,
      "issue": 8,
      "issuetype": 1,
      "grade": 7.5,
      "weight": 1,
      "filename": "SURFER_8"
    },
    {
      "key": -1440,
      "index": 791,
      "title": 22,
      "issue": 59,
      "issuetype": 1,
      "grade": 6,
      "weight": 1,
      "filename": "XMEN_59"
    }
  ]
}